streamcorpus_opensextant
