Metadata-Version: 1.0
Name: streamcorpus-opensextant
Version: 0.2.5
Summary: Transforms for converting opensextant output into Token objects in streamcorpus
Home-page: UNKNOWN
Author: Diffeo, Inc.
Author-email: support@diffeo.com
License: UNKNOWN
Platform: UNKNOWN
